{
	"apiVersion": 2,
	"name": "camino-blocks-plugin/testimonials",
	"title": "Camino - Testimonials",
	"category": "widgets",
	"icon": "insert",
	"description": "Display testimonials slider",
	"keywords": ["testimonials"],
	"supports": {
		"html": false
	},
	"textdomain": "camino-blocks-plugin",
	"editorScript": "file:./build/index.js",
	"editorStyle": "file:./build/index.css",
	"style": "file:./build/style-index.css",
	"attributes": {
		"fullBackground": {
			"type": "boolean"
		},
		"halfBackground": {
			"type": "boolean"
		}
	}
}